anujscan/__init__.py
anujscan/__main__.py
anujscan/modules/__init__.py
anujscan/modules/dir_bruteforce.py
anujscan/modules/http_headers.py
anujscan/modules/port_scanner.py
anujscan/modules/ssl_checker.py
anujscan/modules/subdomain_scan.py
anujscan/modules/whois_lookup.py
anujscanpro-0.1.0.dist-info/licenses/LICENSE
anujscanpro-0.1.0.dist-info/METADATA
anujscanpro-0.1.0.dist-info/WHEEL
anujscanpro-0.1.0.dist-info/entry_points.txt
anujscanpro-0.1.0.dist-info/top_level.txt
anujscanpro-0.1.0.dist-info/RECORD
