Metadata-Version: 2.4
Name: anujscanpro
Version: 0.1.0
Summary: AnujScan Pro - A modular recon & vulnerability analysis toolkit
Home-page: https://github.com/yourusername/anujscan
Author: Anuj Prajapati
Author-email: your-email@example.com
Classifier: Programming Language :: Python :: 3
Classifier: License :: OSI Approved :: MIT License
Classifier: Operating System :: OS Independent
Requires-Python: >=3.7
License-File: LICENSE
Requires-Dist: pyfiglet
Requires-Dist: colorama
Requires-Dist: yaspin
Requires-Dist: requests
Requires-Dist: dnspython
Dynamic: author
Dynamic: author-email
Dynamic: classifier
Dynamic: description
Dynamic: description-content-type
Dynamic: home-page
Dynamic: license-file
Dynamic: requires-dist
Dynamic: requires-python
Dynamic: summary
